{
  "AssetManager": {
    "Assets": [
      {
        "GUID": "bg1"
      },
      {
        "GUID": "wizSprite"
      }
    ]
  },
  "Scene": {
    "Name": "Level02",
    "GUID": "45f479c9-f110-43c5-be35-9fbbc5d7d694",
    "IsEnabled": false,
    "Entities": [
      {
        "Name": "Background",
        "GUID": "bgimage1",
        "Transform": {
          "Position": [ 350.0, 350.0 ],
          "Rotation": 0.0,
          "Scale": [ 1.0, 1.0 ]
        },
        "Components": [
          {
            "ClassName": "Sprite",
            "ClassData": {
              "Texture": "bg1"
            }
          }
        ]
      },
      {
        "Name": "Player",
        "GUID": "playerLevel02",
        "Transform": {
          "Position": [ 65.625, 634.375 ],
          "Rotation": 0.0,
          "Scale": [ 0.9, 0.9 ]
        },
        "Components": [
          {
            "ClassName": "Sprite",
            "ClassData": {
              "Texture": "wizSprite"
            }
          },
          {
            "ClassName": "BoxCollider",
            "ClassData": {}
          },
          {
            "ClassName": "Player",
            "ClassData": {
              "Speed": 400.0,
              "DeathScene": "45f479c9-f110-43c5-be35-9fbbc5d7d694"
            }
          }
        ]
      },
      {
        "Name": "Portal",
        "GUID": "p1",
        "Transform": {
          "Position": [ 634.375, 634.375 ],
          "Rotation": 0.0,
          "Scale": [ 0.9, 0.9 ]
        },
        "Components": [
          {
            "ClassName": "Sprite",
            "ClassData": {
              "Texture": "portal"
            }
          },
          {
            "ClassName": "BoxCollider",
            "ClassData": {}
          },
          {
            "ClassName": "Portal",
            "ClassData": {
              "NextScene": "632b2afd-2ffe-4776-83f3-2138a446b46a"
            }
          }
        ]
      }
    ]
  }
}